dbt/adapters/clickhouse/__init__.py
dbt/adapters/clickhouse/__version__.py
dbt/adapters/clickhouse/cache.py
dbt/adapters/clickhouse/column.py
dbt/adapters/clickhouse/connections.py
dbt/adapters/clickhouse/credentials.py
dbt/adapters/clickhouse/dbclient.py
dbt/adapters/clickhouse/errors.py
dbt/adapters/clickhouse/httpclient.py
dbt/adapters/clickhouse/impl.py
dbt/adapters/clickhouse/logger.py
dbt/adapters/clickhouse/nativeclient.py
dbt/adapters/clickhouse/query.py
dbt/adapters/clickhouse/relation.py
dbt/adapters/clickhouse/util.py
dbt/include/clickhouse/__init__.py
dbt/include/clickhouse/dbt_project.yml
dbt/include/clickhouse/macros/adapters.sql
dbt/include/clickhouse/macros/catalog.sql
dbt/include/clickhouse/macros/column_spec_ddl.sql
dbt/include/clickhouse/macros/persist_docs.sql
dbt/include/clickhouse/macros/adapters/apply_grants.sql
dbt/include/clickhouse/macros/adapters/relation.sql
dbt/include/clickhouse/macros/materializations/dictionary.sql
dbt/include/clickhouse/macros/materializations/distributed_table.sql
dbt/include/clickhouse/macros/materializations/materialized_view.sql
dbt/include/clickhouse/macros/materializations/s3.sql
dbt/include/clickhouse/macros/materializations/seed.sql
dbt/include/clickhouse/macros/materializations/snapshot.sql
dbt/include/clickhouse/macros/materializations/table.sql
dbt/include/clickhouse/macros/materializations/view.sql
dbt/include/clickhouse/macros/materializations/incremental/distributed_incremental.sql
dbt/include/clickhouse/macros/materializations/incremental/incremental.sql
dbt/include/clickhouse/macros/materializations/incremental/is_incremental.sql
dbt/include/clickhouse/macros/materializations/incremental/schema_changes.sql
dbt/include/clickhouse/macros/schema_tests/relationships.sql
dbt/include/clickhouse/macros/utils/datatypes.sql
dbt/include/clickhouse/macros/utils/timestamps.sql
dbt/include/clickhouse/macros/utils/utils.sql
dbt_bytehouse-1.8.9.dist-info/LICENSE
dbt_bytehouse-1.8.9.dist-info/METADATA
dbt_bytehouse-1.8.9.dist-info/WHEEL
dbt_bytehouse-1.8.9.dist-info/top_level.txt
dbt_bytehouse-1.8.9.dist-info/RECORD
