Metadata-Version: 2.2
Name: dbt-bytehouse
Version: 1.8.9
Summary: The Clickhouse plugin for dbt (data build tool)
Home-page: https://github.com/ClickHouse/dbt-clickhouse
Author: ClickHouse Inc.
Author-email: guy@clickhouse.com
License: MIT
Platform: any
Classifier: Development Status :: 5 - Production/Stable
Classifier: License :: OSI Approved :: Apache Software License
Classifier: Operating System :: Microsoft :: Windows
Classifier: Operating System :: MacOS :: MacOS X
Classifier: Operating System :: POSIX :: Linux
Classifier: Programming Language :: Python :: 3.9
Classifier: Programming Language :: Python :: 3.10
Classifier: Programming Language :: Python :: 3.11
Classifier: Programming Language :: Python :: 3.12
Requires-Python: >=3.9
License-File: LICENSE
Requires-Dist: dbt-core~=1.8.0
Requires-Dist: bytehouse-connect>=0.8.6
Requires-Dist: clickhouse-driver>=0.2.6
Requires-Dist: setuptools>=0.69
Dynamic: author
Dynamic: author-email
Dynamic: classifier
Dynamic: description
Dynamic: description-content-type
Dynamic: home-page
Dynamic: license
Dynamic: platform
Dynamic: requires-dist
Dynamic: requires-python
Dynamic: summary
